MANIFEST.in
README.rst
emulaterest.py
setup.py
tests.py
emulaterest.egg-info/PKG-INFO
emulaterest.egg-info/SOURCES.txt
emulaterest.egg-info/dependency_links.txt
emulaterest.egg-info/entry_points.txt
emulaterest.egg-info/top_level.txt