Metadata-Version: 1.0
Name: emulaterest
Version: 0.1
Summary: WSGI middleware that does Rails style PUT and DELETE request emulation
Home-page: http://github.com/abiczo/emulaterest
Author: Andras Biczo
Author-email: abiczo@gmail.com
License: MIT
Keywords: web wsgi middleware rest
Platform: UNKNOWN
Classifier: Development Status :: 3 - Alpha
Classifier: Environment :: Web Environment
Classifier: Intended Audience :: Developers
Classifier: License :: OSI Approved :: MIT License
Classifier: Programming Language :: Python
Classifier: Topic :: Internet :: WWW/HTTP :: WSGI :: Middleware
Classifier: Topic :: Software Development :: Libraries :: Python Modules
